arcticdem/__init__.py
arcticdem/arcticdem.py
arcticdem/arcticdem_async_unpack.py
arcticdem/arcticdem_download.py
arcticdem/arcticdem_extract.py
arcticdem/arcticdem_init.py
arcticdem/arcticdem_size.py
arcticdem-0.2.0.dist-info/LICENSE
arcticdem-0.2.0.dist-info/METADATA
arcticdem-0.2.0.dist-info/WHEEL
arcticdem-0.2.0.dist-info/entry_points.txt
arcticdem-0.2.0.dist-info/top_level.txt
arcticdem-0.2.0.dist-info/RECORD
