Metadata-Version: 2.1
Name: arcticdem
Version: 0.2.0
Summary: ArcticDEM Batch Download & Processing Tools
Home-page: https://github.com/samapriya/ArcticDEM-Batch-Pipeline
Author: Samapriya Roy
Author-email: samapriya.roy@gmail.com
License: Apache 2.0
Platform: UNKNOWN
Classifier: Development Status :: 3 - Alpha
Classifier: Intended Audience :: Developers
Classifier: Intended Audience :: Science/Research
Classifier: Natural Language :: English
Classifier: License :: OSI Approved :: Apache Software License
Classifier: Programming Language :: Python
Classifier: Programming Language :: Python :: 3.5
Classifier: Programming Language :: Python :: 3.6
Classifier: Operating System :: OS Independent
Classifier: Topic :: Scientific/Engineering :: GIS
Requires-Python: >=3.4
Requires-Dist: requests (>=2.21.1)
Requires-Dist: progressbar2 (>=3.38.0)
Requires-Dist: beautifulsoup4
Requires-Dist: retrying (>=1.3.3)
Requires-Dist: pyproj (>=1.9.5.1) ; platform_system != "Windows"
Requires-Dist: shapely (>=1.6.4) ; platform_system != "Windows"
Requires-Dist: fiona (>=1.8.6) ; platform_system != "Windows"
Requires-Dist: geopandas (>=0.5.0) ; platform_system != "Windows"
Requires-Dist: Rtree-linux (>=0.9.4) ; platform_system == "Linux"
